antsi-0.2.1.dist-info/METADATA
antsi-0.2.1.dist-info/WHEEL
antsi-0.2.1.dist-info/license_files/LICENSE.md
antsi/py.typed
antsi/_antsi.pyi
antsi/__init__.py
antsi/_antsi.abi3.so
antsi-0.2.1.dist-info/RECORD
