Metadata-Version: 2.3
Name: antsi
Version: 0.2.1
Classifier: Programming Language :: Rust
Classifier: Programming Language :: Python :: Implementation :: CPython
Classifier: Programming Language :: Python :: Implementation :: PyPy
License-File: LICENSE.md
Summary: A quick and user-friendly way to style your text using ANSI codes
Author-email: Alex Krantz <alex@krantz.dev>
License: MIT
Requires-Python: >=3.10
Project-URL: homepage, https://github.com/akrantz01/antsi
Project-URL: issues, https://github.com/akrantz01/antsi/issues
